jinja2_pdoc/__init__.py
jinja2_pdoc/cli.py
jinja2_pdoc/environment.py
jinja2_pdoc/extension.py
jinja2_pdoc/meta.py
jinja2_pdoc/wrapper.py
jinja2_pdoc-1.3.0.dist-info/LICENSE
jinja2_pdoc-1.3.0.dist-info/METADATA
jinja2_pdoc-1.3.0.dist-info/WHEEL
jinja2_pdoc-1.3.0.dist-info/entry_points.txt
jinja2_pdoc-1.3.0.dist-info/RECORD
