Metadata-Version: 2.1
Name: jinja2-pdoc
Version: 1.3.0
Summary: jinja2 extension to embedd python code directly from module using pdoc
License: MIT
Keywords: jinja2,pdoc,jinja2 extension,pre-commit-hook
Author: Christoph Dörrer
Author-email: d-chris@web.de
Requires-Python: >=3.8.1,<4.0.0
Classifier: License :: OSI Approved :: MIT License
Classifier: Operating System :: OS Independent
Classifier: Programming Language :: Python :: 3
Classifier: Programming Language :: Python :: 3.9
Classifier: Programming Language :: Python :: 3.10
Classifier: Programming Language :: Python :: 3.11
Classifier: Programming Language :: Python :: 3.12
Classifier: Programming Language :: Python :: 3.13
Classifier: Programming Language :: Python :: 3.8
Requires-Dist: Jinja2 (>=3.1.2,<4.0.0)
Requires-Dist: autopep8 (>=2.0.4,<3.0.0)
Requires-Dist: click (>=8.1.7,<9.0.0)
Requires-Dist: pdoc (>=14.3.0) ; python_version >= "3.9" and python_version < "4.0"
Requires-Dist: pdoc (>=14.3.0,<15.0.0) ; python_version < "3.9"
Requires-Dist: pyyaml (>=6.0.1,<7.0.0)
Project-URL: documentation, https://d-chris.github.io/jinja2_pdoc
Project-URL: repository, https://github.com/d-chris/jinja2_pdoc
